request_manager/manager.py
request_manager/parameters/__init__.py
request_manager/parameters/headers.py
request_manager_attenuare-0.0.3.dist-info/LICENSE.txt
request_manager_attenuare-0.0.3.dist-info/METADATA
request_manager_attenuare-0.0.3.dist-info/WHEEL
request_manager_attenuare-0.0.3.dist-info/top_level.txt
request_manager_attenuare-0.0.3.dist-info/RECORD
