Metadata-Version: 2.1
Name: request-manager-attenuare
Version: 0.0.3
Summary: Class used to manage a specific request to a endpoint, and try again if specific errors appear
Home-page: https://bitbucket.org/nappsolutionsdev/scrapping_model/src/scrapping_model/
Author: Leandro Alves
Author-email: Leandro Alves <leandro.augusto.alves@outlook.com.br>
Project-URL: Homepage, https://github.com/Attenuare/request_manager
Classifier: Programming Language :: Python :: 3
Classifier: License :: OSI Approved :: MIT License
Classifier: Operating System :: OS Independent
Requires-Python: >=3.9
License-File: LICENSE.txt
Requires-Dist: playwright
Requires-Dist: bs4
Requires-Dist: requests
